setup.py
example_server/TwoStageOpAmp.py
example_server/__init__.py
example_server/auto_ckt_sim_lib.py
example_server.egg-info/PKG-INFO
example_server.egg-info/SOURCES.txt
example_server.egg-info/dependency_links.txt
example_server.egg-info/requires.txt
example_server.egg-info/top_level.txt
example_server/mocks/TwoStageOpAmp.py
example_server/mocks/__init__.py
example_server/tests/__init__.py
example_server/tests/test_TwoStageOpAmp.py